{"nodes": [{"y": 248, "x": 577, "size": 3, "id": "Doll12_0", "label": "person"}, {"y": 259, "x": 170, "size": 3, "id": "Doll01_0", "label": "person"}, {"y": 177, "x": 605, "size": 3, "id": "bush_0", "label": "bush"}, {"y": 235, "x": 654, "size": 3, "id": "bush_1", "label": "bush"}, {"y": 255, "x": 119, "size": 3, "id": "log_0", "label": "log"}, {"y": 65, "x": 532, "size": 3, "id": "sun_0", "label": "sun"}, {"y": 260, "x": 258, "size": 3, "id": "sandwich_0", "label": "sandwich"}, {"y": 249, "x": 134, "size": 3, "id": "marshmallow_0", "label": "marshmallow"}, {"y": 222, "x": 468, "size": 3, "id": "marshmallow_1", "label": "marshmallow"}, {"y": 272, "x": 392, "size": 3, "id": "campfire_0", "label": "campfire"}], "edges": [{"source": "Doll12_0", "label": "opposite", "id": 0, "target": "Doll01_0"}, {"source": "Doll01_0", "label": "beside", "id": 11, "target": "log_0"}, {"source": "Doll01_0", "label": "beside", "id": 14, "target": "marshmallow_0"}, {"source": "bush_0", "label": "aboveC", "id": 17, "target": "bush_1"}, {"source": "log_0", "label": "surrounds", "id": 32, "target": "marshmallow_0"}]}