{"nodes": [{"y": 286, "x": 199, "size": 3, "id": "Doll15_0", "label": "person"}, {"y": 337, "x": 59, "size": 3, "id": "Puppy02_0", "label": "Puppy"}, {"y": 381, "x": 276, "size": 2, "id": "Rug_0", "label": "Rug"}, {"y": 104, "x": 96, "size": 3, "id": "Window03_0", "label": "Window"}, {"y": 98, "x": 570, "size": 3, "id": "Window03_1", "label": "Window"}, {"y": 297, "x": 569, "size": 2, "id": "Sofa_0", "label": "Sofa"}, {"y": 246, "x": 509, "size": 3, "id": "Pillow_0", "label": "Pillow"}, {"y": 251, "x": 620, "size": 2, "id": "Pillow_1", "label": "Pillow"}], "edges": [{"source": "Doll15_0", "label": "beside", "id": 0, "target": "Puppy02_0"}, {"source": "Doll15_0", "label": "aboveC", "id": 1, "target": "Rug_0"}, {"source": "Sofa_0", "label": "surrounds", "id": 25, "target": "Pillow_0"}, {"source": "Sofa_0", "label": "surrounds", "id": 26, "target": "Pillow_1"}]}