{"nodes": [{"y": 281, "x": 157, "size": 3, "id": "Doll16_0", "label": "person"}, {"y": 327, "x": 228, "size": 3, "id": "Puppy01_0", "label": "Puppy"}, {"y": 89, "x": 162, "size": 3, "id": "sun_0", "label": "sun"}, {"y": 326, "x": 409, "size": 3, "id": "sidewalk_0", "label": "sidewalk"}, {"y": 166, "x": 235, "size": 3, "id": "bush_0", "label": "bush"}, {"y": 165, "x": 603, "size": 3, "id": "tree_0", "label": "tree"}, {"y": 304, "x": 472, "size": 2, "id": "bike_0", "label": "bike"}, {"y": 179, "x": 612, "size": 3, "id": "nest_0", "label": "nest"}, {"y": 267, "x": 165, "size": 3, "id": "apple_0", "label": "apple"}], "edges": [{"source": "Doll16_0", "label": "near", "id": 0, "target": "Puppy01_0"}, {"source": "Doll16_0", "label": "belowC", "id": 7, "target": "apple_0"}, {"source": "Puppy01_0", "label": "on", "id": 9, "target": "sidewalk_0"}, {"source": "sidewalk_0", "label": "beside", "id": 23, "target": "bike_0"}, {"source": "tree_0", "label": "surrounds", "id": 31, "target": "nest_0"}]}