{"nodes": [{"y": 225, "x": 567, "size": 3, "id": "Doll08_0", "label": "person"}, {"y": 196, "x": 160, "size": 3, "id": "Doll14_0", "label": "person"}, {"y": 181, "x": 387, "size": 3, "id": "Doll15_0", "label": "person"}, {"y": 295, "x": 148, "size": 3, "id": "bike_0", "label": "bike"}, {"y": 150, "x": 600, "size": 3, "id": "tree_0", "label": "tree"}, {"y": 46, "x": 79, "size": 3, "id": "sun_0", "label": "sun"}, {"y": 48, "x": 149, "size": 3, "id": "cloud_0", "label": "cloud"}, {"y": 323, "x": 189, "size": 3, "id": "sidewalk_0", "label": "sidewalk"}, {"y": 263, "x": 537, "size": 3, "id": "bench_0", "label": "bench"}, {"y": 185, "x": 345, "size": 3, "id": "football_0", "label": "football"}], "edges": [{"source": "Doll08_0", "label": "opposite", "id": 0, "target": "Doll14_0"}, {"source": "Doll08_0", "label": "near", "id": 1, "target": "Doll15_0"}, {"source": "tree_0", "label": "surrounds", "id": 3, "target": "Doll08_0"}, {"source": "Doll08_0", "label": "on", "id": 7, "target": "bench_0"}, {"source": "Doll14_0", "label": "opposite", "id": 9, "target": "Doll15_0"}, {"source": "Doll14_0", "label": "above", "id": 10, "target": "bike_0"}, {"source": "Doll14_0", "label": "above", "id": 14, "target": "sidewalk_0"}, {"source": "Doll14_0", "label": "near", "id": 16, "target": "football_0"}, {"source": "Doll15_0", "label": "near", "id": 22, "target": "bench_0"}, {"source": "Doll15_0", "label": "beside", "id": 23, "target": "football_0"}, {"source": "bike_0", "label": "on", "id": 27, "target": "sidewalk_0"}]}