{"nodes": [{"y": 216, "x": 112, "size": 3, "id": "Doll04_0", "label": "person"}, {"y": 328, "x": 258, "size": 3, "id": "Kitten01_0", "label": "Kitten"}, {"y": 122, "x": 342, "size": 3, "id": "Window05_0", "label": "Window"}, {"y": 115, "x": 552, "size": 3, "id": "Picture_0", "label": "Picture"}, {"y": 255, "x": 124, "size": 3, "id": "Chair02_0", "label": "Chair"}, {"y": 273, "x": 630, "size": 3, "id": "CoatRack_0", "label": "CoatRack"}], "edges": [{"source": "Doll04_0", "label": "near", "id": 0, "target": "Kitten01_0"}, {"source": "Doll04_0", "label": "on", "id": 3, "target": "Chair02_0"}]}