{"nodes": [{"y": 176, "x": 574, "size": 3, "id": "Doll01_0", "label": "person"}, {"y": 158, "x": 367, "size": 3, "id": "Picture_0", "label": "Picture"}, {"y": 119, "x": 100, "size": 3, "id": "Window05_0", "label": "Window"}, {"y": 195, "x": 281, "size": 3, "id": "Plant_0", "label": "Plant"}, {"y": 196, "x": 453, "size": 3, "id": "Plant_1", "label": "Plant"}, {"y": 273, "x": 364, "size": 3, "id": "CoffeeTable_0", "label": "CoffeeTable"}, {"y": 227, "x": 416, "size": 3, "id": "wine_0", "label": "wine"}], "edges": [{"source": "Doll01_0", "label": "beside", "id": 3, "target": "Plant_1"}, {"source": "Doll01_0", "label": "near", "id": 5, "target": "wine_0"}, {"source": "Picture_0", "label": "aboveC", "id": 9, "target": "CoffeeTable_0"}, {"source": "wine_0", "label": "belowC", "id": 10, "target": "Picture_0"}]}