{"nodes": [{"y": 257, "x": 534, "size": 3, "id": "Doll04_0", "label": "person"}, {"y": 209, "x": 94, "size": 3, "id": "Frog_0", "label": "Frog"}, {"y": 266, "x": 342, "size": 3, "id": "Frog_1", "label": "Frog"}, {"y": 194, "x": 302, "size": 3, "id": "Duck02_0", "label": "Duck"}, {"y": 182, "x": 236, "size": 3, "id": "Koi_0", "label": "Koi"}, {"y": 260, "x": 211, "size": 3, "id": "Koi_1", "label": "Koi"}, {"y": 345, "x": 211, "size": 3, "id": "Koi_2", "label": "Koi"}, {"y": 190, "x": 285, "size": 3, "id": "pond_0", "label": "pond"}, {"y": 263, "x": 205, "size": 3, "id": "pond_1", "label": "pond"}, {"y": 347, "x": 244, "size": 3, "id": "pond_2", "label": "pond"}, {"y": 26, "x": 76, "size": 3, "id": "sun_0", "label": "sun"}, {"y": 149, "x": 572, "size": 3, "id": "tree_0", "label": "tree"}, {"y": 115, "x": 615, "size": 1, "id": "tree_1", "label": "tree"}, {"y": 179, "x": 665, "size": 3, "id": "bush_0", "label": "bush"}, {"y": 228, "x": 661, "size": 3, "id": "bush_1", "label": "bush"}, {"y": 280, "x": 657, "size": 3, "id": "bush_2", "label": "bush"}, {"y": 325, "x": 622, "size": 3, "id": "bush_3", "label": "bush"}, {"y": 368, "x": 574, "size": 3, "id": "bush_4", "label": "bush"}, {"y": 58, "x": 232, "size": 3, "id": "cloud_0", "label": "cloud"}], "edges": [{"source": "Doll04_0", "label": "opposite", "id": 2, "target": "Duck02_0"}, {"source": "Doll04_0", "label": "on", "id": 10, "target": "tree_0"}, {"source": "Doll04_0", "label": "above", "id": 16, "target": "bush_4"}, {"source": "Duck02_0", "label": "beside", "id": 51, "target": "Koi_0"}, {"source": "Duck02_0", "label": "above", "id": 53, "target": "Koi_2"}, {"source": "pond_0", "label": "surrounds", "id": 54, "target": "Duck02_0"}, {"source": "Koi_0", "label": "above", "id": 66, "target": "Koi_1"}, {"source": "Koi_0", "label": "above", "id": 67, "target": "Koi_2"}, {"source": "pond_0", "label": "surrounds", "id": 68, "target": "Koi_0"}, {"source": "Koi_1", "label": "above", "id": 80, "target": "Koi_2"}, {"source": "pond_1", "label": "surrounds", "id": 82, "target": "Koi_1"}, {"source": "pond_2", "label": "surrounds", "id": 95, "target": "Koi_2"}, {"source": "tree_0", "label": "beside_infront", "id": 143, "target": "tree_1"}, {"source": "bush_0", "label": "aboveC", "id": 156, "target": "bush_1"}, {"source": "bush_1", "label": "aboveC", "id": 161, "target": "bush_2"}, {"source": "bush_2", "label": "on", "id": 165, "target": "bush_3"}]}