{"nodes": [{"y": 300, "x": 181, "size": 3, "id": "Doll06_0", "label": "person"}, {"y": 319, "x": 418, "size": 3, "id": "Dog01_0", "label": "Dog"}, {"y": 337, "x": 348, "size": 3, "id": "Rug_0", "label": "Rug"}, {"y": 71, "x": 333, "size": 3, "id": "Picture_0", "label": "Picture"}, {"y": 234, "x": 341, "size": 3, "id": "Fireplace_0", "label": "Fireplace"}, {"y": 107, "x": 563, "size": 3, "id": "Window05_0", "label": "Window"}, {"y": 105, "x": 101, "size": 3, "id": "Window05_1", "label": "Window"}, {"y": 163, "x": 570, "size": 3, "id": "Plant_0", "label": "Plant"}, {"y": 169, "x": 100, "size": 3, "id": "Plant_1", "label": "Plant"}, {"y": 234, "x": 564, "size": 3, "id": "Desk_0", "label": "Desk"}, {"y": 241, "x": 100, "size": 3, "id": "Desk_1", "label": "Desk"}, {"y": 279, "x": 232, "size": 3, "id": "DogBone_0", "label": "DogBone"}], "edges": [{"source": "Doll06_0", "label": "near", "id": 0, "target": "Dog01_0"}, {"source": "Doll06_0", "label": "near", "id": 1, "target": "Rug_0"}, {"source": "Doll06_0", "label": "near", "id": 3, "target": "Fireplace_0"}, {"source": "Doll06_0", "label": "beside", "id": 9, "target": "Desk_1"}, {"source": "Doll06_0", "label": "beside", "id": 10, "target": "DogBone_0"}, {"source": "Dog01_0", "label": "on", "id": 11, "target": "Rug_0"}, {"source": "Dog01_0", "label": "below", "id": 13, "target": "Fireplace_0"}, {"source": "Rug_0", "label": "belowC", "id": 22, "target": "Fireplace_0"}, {"source": "Window05_0", "label": "aboveC", "id": 46, "target": "Plant_0"}, {"source": "Window05_1", "label": "aboveC", "id": 52, "target": "Plant_1"}, {"source": "Plant_0", "label": "aboveC", "id": 57, "target": "Desk_0"}, {"source": "Plant_1", "label": "aboveC", "id": 61, "target": "Desk_1"}]}