{"nodes": [{"y": 175, "x": 484, "size": 1, "id": "Doll18_0", "label": "person"}, {"y": 139, "x": 311, "size": 1, "id": "Doll13_0", "label": "person"}, {"y": 165, "x": 384, "size": 5, "id": "monkeybars_0", "label": "monkeybars"}, {"y": 134, "x": 22, "size": 3, "id": "bush_0", "label": "bush"}, {"y": 150, "x": 82, "size": 3, "id": "bush_1", "label": "bush"}, {"y": 39, "x": 619, "size": 3, "id": "cloud_0", "label": "cloud"}, {"y": 43, "x": 122, "size": 2, "id": "sun_0", "label": "sun"}, {"y": 228, "x": 83, "size": 3, "id": "log_0", "label": "log"}, {"y": 344, "x": 521, "size": 2, "id": "sidewalk_0", "label": "sidewalk"}, {"y": 284, "x": 30, "size": 3, "id": "flower_0", "label": "flower"}], "edges": [{"source": "Doll18_0", "label": "near", "id": 0, "target": "Doll13_0"}, {"source": "monkeybars_0", "label": "surrounds", "id": 1, "target": "Doll18_0"}, {"source": "Doll18_0", "label": "above", "id": 7, "target": "sidewalk_0"}, {"source": "monkeybars_0", "label": "surrounds", "id": 9, "target": "Doll13_0"}, {"source": "bush_1", "label": "surrounds", "id": 24, "target": "bush_0"}]}