{"nodes": [{"y": 170, "x": 380, "size": 2, "id": "Door_0", "label": "Door"}, {"y": 250, "x": 113, "size": 3, "id": "Plant_0", "label": "Plant"}, {"y": 353, "x": 103, "size": 2, "id": "Table_0", "label": "Table"}, {"y": 370, "x": 363, "size": 2, "id": "Rug_0", "label": "Rug"}, {"y": 310, "x": 646, "size": 2, "id": "Sofa_0", "label": "Sofa"}, {"y": 101, "x": 126, "size": 3, "id": "Window03_0", "label": "Window"}], "edges": [{"source": "Plant_0", "label": "aboveC", "id": 5, "target": "Table_0"}, {"source": "Plant_0", "label": "belowC", "id": 8, "target": "Window03_0"}, {"source": "Table_0", "label": "below", "id": 11, "target": "Window03_0"}]}