{"nodes": [{"y": 242, "x": 656, "size": 3, "id": "Doll17_0", "label": "person"}, {"y": 220, "x": 406, "size": 1, "id": "CoatRack_0", "label": "CoatRack"}, {"y": 268, "x": 539, "size": 3, "id": "CoffeeTable_0", "label": "CoffeeTable"}, {"y": 260, "x": 669, "size": 3, "id": "DiningChair_0", "label": "DiningChair"}, {"y": 156, "x": 59, "size": 3, "id": "Bookshelf_0", "label": "Bookshelf"}, {"y": 155, "x": 244, "size": 3, "id": "Bookshelf_1", "label": "Bookshelf"}, {"y": 349, "x": 532, "size": 3, "id": "Rug_0", "label": "Rug"}, {"y": 243, "x": 535, "size": 3, "id": "Notebook_0", "label": "Notebook"}, {"y": 237, "x": 557, "size": 3, "id": "Notebook_1", "label": "Notebook"}, {"y": 218, "x": 515, "size": 3, "id": "Notebook_2", "label": "Notebook"}, {"y": 204, "x": 546, "size": 3, "id": "Stapler_0", "label": "Stapler"}], "edges": [{"source": "Doll17_0", "label": "beside", "id": 1, "target": "CoffeeTable_0"}, {"source": "Doll17_0", "label": "on", "id": 2, "target": "DiningChair_0"}, {"source": "Doll17_0", "label": "beside", "id": 6, "target": "Notebook_0"}, {"source": "Doll17_0", "label": "beside", "id": 7, "target": "Notebook_1"}, {"source": "Doll17_0", "label": "beside", "id": 8, "target": "Notebook_2"}, {"source": "Doll17_0", "label": "beside", "id": 9, "target": "Stapler_0"}, {"source": "CoffeeTable_0", "label": "aboveC", "id": 22, "target": "Rug_0"}, {"source": "CoffeeTable_0", "label": "surrounds", "id": 23, "target": "Notebook_0"}, {"source": "CoffeeTable_0", "label": "surrounds", "id": 24, "target": "Notebook_1"}, {"source": "CoffeeTable_0", "label": "surrounds", "id": 25, "target": "Notebook_2"}, {"source": "Stapler_0", "label": "on", "id": 26, "target": "CoffeeTable_0"}, {"source": "Notebook_0", "label": "aboveC", "id": 45, "target": "Rug_0"}, {"source": "Notebook_1", "label": "aboveC", "id": 46, "target": "Rug_0"}, {"source": "Notebook_2", "label": "aboveC", "id": 47, "target": "Rug_0"}, {"source": "Stapler_0", "label": "aboveC", "id": 48, "target": "Rug_0"}, {"source": "Notebook_0", "label": "belowC", "id": 50, "target": "Notebook_2"}, {"source": "Notebook_0", "label": "belowC", "id": 51, "target": "Stapler_0"}, {"source": "Notebook_1", "label": "belowC", "id": 53, "target": "Stapler_0"}]}