{"nodes": [{"y": 197, "x": 118, "size": 1, "id": "Doll03_0", "label": "person"}, {"y": 283, "x": 477, "size": 3, "id": "Kitten01_0", "label": "Kitten"}, {"y": 328, "x": 141, "size": 3, "id": "Sofa_0", "label": "Sofa"}, {"y": 285, "x": 263, "size": 1, "id": "Stool_0", "label": "Stool"}, {"y": 210, "x": 558, "size": 1, "id": "Plant_0", "label": "Plant"}, {"y": 230, "x": 361, "size": 3, "id": "Fireplace_0", "label": "Fireplace"}, {"y": 78, "x": 365, "size": 3, "id": "Picture_0", "label": "Picture"}, {"y": 166, "x": 365, "size": 3, "id": "DishesMeal_0", "label": "DishesMeal"}], "edges": [{"source": "Doll03_0", "label": "above_behind", "id": 1, "target": "Sofa_0"}, {"source": "DishesMeal_0", "label": "aboveC", "id": 26, "target": "Fireplace_0"}, {"source": "DishesMeal_0", "label": "belowC", "id": 27, "target": "Picture_0"}]}