{"nodes": [{"y": 230, "x": 328, "size": 3, "id": "Doll18_0", "label": "person"}, {"y": 151, "x": 427, "size": 3, "id": "Doll03_0", "label": "person"}, {"y": 73, "x": 95, "size": 3, "id": "Hawk_0", "label": "Hawk"}, {"y": 168, "x": 106, "size": 3, "id": "Eagle_0", "label": "Eagle"}, {"y": 366, "x": 499, "size": 3, "id": "Koi_0", "label": "Koi"}, {"y": 343, "x": 541, "size": 3, "id": "Pigeon_0", "label": "Pigeon"}, {"y": 373, "x": 201, "size": 3, "id": "bench_0", "label": "bench"}, {"y": 144, "x": 441, "size": 3, "id": "bush_0", "label": "bush"}, {"y": 136, "x": 576, "size": 3, "id": "bush_1", "label": "bush"}, {"y": 22, "x": 681, "size": 3, "id": "sun_0", "label": "sun"}, {"y": 366, "x": 501, "size": 3, "id": "pond_0", "label": "pond"}, {"y": 64, "x": 246, "size": 3, "id": "tree_0", "label": "tree"}], "edges": [{"source": "Doll18_0", "label": "near", "id": 0, "target": "Doll03_0"}, {"source": "Doll03_0", "label": "beside", "id": 16, "target": "bush_0"}, {"source": "pond_0", "label": "surrounds", "id": 43, "target": "Koi_0"}, {"source": "pond_0", "label": "surrounds", "id": 49, "target": "Pigeon_0"}]}