{"nodes": [{"y": 148, "x": 501, "size": 3, "id": "Doll18_0", "label": "person"}, {"y": 273, "x": 617, "size": 3, "id": "Doll12_0", "label": "person"}, {"y": 50, "x": 552, "size": 3, "id": "Eagle_0", "label": "Eagle"}, {"y": 266, "x": 269, "size": 3, "id": "Duck01_0", "label": "Duck"}, {"y": 259, "x": 200, "size": 3, "id": "Frog_0", "label": "Frog"}, {"y": 249, "x": 209, "size": 3, "id": "pond_0", "label": "pond"}, {"y": 162, "x": 90, "size": 3, "id": "bush_0", "label": "bush"}, {"y": 146, "x": 287, "size": 3, "id": "bush_1", "label": "bush"}, {"y": 150, "x": 397, "size": 3, "id": "bush_2", "label": "bush"}, {"y": 154, "x": 504, "size": 3, "id": "bush_3", "label": "bush"}, {"y": 162, "x": 608, "size": 3, "id": "bush_4", "label": "bush"}, {"y": 96, "x": 168, "size": 3, "id": "tree_0", "label": "tree"}, {"y": 96, "x": 674, "size": 3, "id": "tree_1", "label": "tree"}, {"y": 107, "x": 31, "size": 3, "id": "tree_2", "label": "tree"}, {"y": 85, "x": 380, "size": 3, "id": "tree_3", "label": "tree"}, {"y": 196, "x": 76, "size": 3, "id": "sandbox_0", "label": "sandbox"}, {"y": 196, "x": 286, "size": 3, "id": "sandbox_1", "label": "sandbox"}, {"y": 197, "x": 500, "size": 3, "id": "sandbox_2", "label": "sandbox"}, {"y": 198, "x": 709, "size": 3, "id": "sandbox_3", "label": "sandbox"}, {"y": 261, "x": 548, "size": 3, "id": "monkeybars_0", "label": "monkeybars"}, {"y": 324, "x": 405, "size": 3, "id": "scooter_0", "label": "scooter"}, {"y": 312, "x": 332, "size": 3, "id": "basket_0", "label": "basket"}, {"y": 294, "x": 590, "size": 3, "id": "cup_0", "label": "cup"}], "edges": [{"source": "Doll18_0", "label": "above", "id": 0, "target": "Doll12_0"}, {"source": "bush_3", "label": "surrounds", "id": 8, "target": "Doll18_0"}, {"source": "Doll18_0", "label": "aboveC", "id": 16, "target": "sandbox_2"}, {"source": "Doll18_0", "label": "above", "id": 18, "target": "monkeybars_0"}, {"source": "Doll18_0", "label": "above", "id": 21, "target": "cup_0"}, {"source": "monkeybars_0", "label": "surrounds", "id": 39, "target": "Doll12_0"}, {"source": "Doll12_0", "label": "beside", "id": 42, "target": "cup_0"}, {"source": "pond_0", "label": "surrounds", "id": 64, "target": "Duck01_0"}, {"source": "Duck01_0", "label": "belowC", "id": 75, "target": "sandbox_1"}, {"source": "pond_0", "label": "surrounds", "id": 82, "target": "Frog_0"}, {"source": "bush_0", "label": "on", "id": 121, "target": "tree_0"}, {"source": "bush_0", "label": "on", "id": 123, "target": "tree_2"}, {"source": "bush_0", "label": "on", "id": 125, "target": "sandbox_0"}, {"source": "bush_1", "label": "aboveC", "id": 141, "target": "sandbox_1"}, {"source": "tree_3", "label": "surrounds", "id": 153, "target": "bush_2"}, {"source": "bush_3", "label": "aboveC", "id": 169, "target": "sandbox_2"}, {"source": "bush_4", "label": "on", "id": 176, "target": "tree_1"}, {"source": "bush_4", "label": "on", "id": 183, "target": "monkeybars_0"}, {"source": "sandbox_2", "label": "on", "id": 239, "target": "monkeybars_0"}, {"source": "monkeybars_0", "label": "surrounds", "id": 249, "target": "cup_0"}, {"source": "basket_0", "label": "on", "id": 250, "target": "scooter_0"}]}