{"nodes": [{"y": 202, "x": 521, "size": 3, "id": "Doll16_0", "label": "person"}, {"y": 39, "x": 340, "size": 5, "id": "Finch_0", "label": "Finch"}, {"y": 231, "x": 630, "size": 3, "id": "Dog02_0", "label": "Dog"}, {"y": 166, "x": 116, "size": 3, "id": "tree_0", "label": "tree"}, {"y": 242, "x": 330, "size": 3, "id": "pond_0", "label": "pond"}, {"y": 169, "x": 596, "size": 3, "id": "soccer_0", "label": "soccer"}], "edges": [{"source": "Doll16_0", "label": "near", "id": 1, "target": "Dog02_0"}, {"source": "Doll16_0", "label": "near", "id": 4, "target": "soccer_0"}, {"source": "Dog02_0", "label": "belowC", "id": 11, "target": "soccer_0"}]}