{"nodes": [{"y": 322, "x": 352, "size": 3, "id": "Doll20_0", "label": "person"}, {"y": 162, "x": 627, "size": 3, "id": "Door_0", "label": "Door"}, {"y": 95, "x": 125, "size": 3, "id": "Picture_0", "label": "Picture"}, {"y": 189, "x": 305, "size": 3, "id": "Picture_1", "label": "Picture"}, {"y": 88, "x": 468, "size": 3, "id": "Picture_2", "label": "Picture"}, {"y": 343, "x": 332, "size": 3, "id": "Rug_0", "label": "Rug"}, {"y": 240, "x": 502, "size": 3, "id": "Plant_0", "label": "Plant"}], "edges": [{"source": "Doll20_0", "label": "near", "id": 0, "target": "Door_0"}, {"source": "Doll20_0", "label": "belowC", "id": 2, "target": "Picture_1"}, {"source": "Doll20_0", "label": "on", "id": 4, "target": "Rug_0"}]}