{"nodes": [{"y": 221, "x": 448, "size": 3, "id": "Doll17_0", "label": "person"}, {"y": 216, "x": 122, "size": 3, "id": "Doll11_0", "label": "person"}, {"y": 243, "x": 556, "size": 3, "id": "Doll15_0", "label": "person"}, {"y": 336, "x": 187, "size": 3, "id": "sidewalk_0", "label": "sidewalk"}, {"y": 331, "x": 642, "size": 3, "id": "sidewalk_1", "label": "sidewalk"}, {"y": 299, "x": 152, "size": 3, "id": "bike_0", "label": "bike"}, {"y": 181, "x": 689, "size": 1, "id": "bush_0", "label": "bush"}, {"y": 364, "x": 406, "size": 3, "id": "bush_1", "label": "bush"}, {"y": 53, "x": 634, "size": 3, "id": "sun_0", "label": "sun"}, {"y": 130, "x": 266, "size": 3, "id": "tree_0", "label": "tree"}, {"y": 292, "x": 599, "size": 1, "id": "skateboard_0", "label": "skateboard"}, {"y": 277, "x": 402, "size": 1, "id": "skateboard_1", "label": "skateboard"}], "edges": [{"source": "Doll17_0", "label": "opposite", "id": 0, "target": "Doll11_0"}, {"source": "Doll17_0", "label": "near", "id": 1, "target": "Doll15_0"}, {"source": "Doll17_0", "label": "above", "id": 6, "target": "bush_1"}, {"source": "Doll17_0", "label": "near_infront", "id": 9, "target": "skateboard_0"}, {"source": "Doll17_0", "label": "above_infront", "id": 10, "target": "skateboard_1"}, {"source": "Doll11_0", "label": "opposite", "id": 11, "target": "Doll15_0"}, {"source": "Doll11_0", "label": "above", "id": 12, "target": "sidewalk_0"}, {"source": "Doll11_0", "label": "above", "id": 14, "target": "bike_0"}, {"source": "tree_0", "label": "surrounds", "id": 18, "target": "Doll11_0"}, {"source": "Doll15_0", "label": "above", "id": 22, "target": "sidewalk_1"}, {"source": "Doll15_0", "label": "above_infront", "id": 28, "target": "skateboard_0"}, {"source": "Doll15_0", "label": "near_infront", "id": 29, "target": "skateboard_1"}, {"source": "sidewalk_0", "label": "belowC", "id": 31, "target": "bike_0"}, {"source": "sidewalk_1", "label": "surrounds", "id": 43, "target": "skateboard_0"}]}