{"nodes": [{"y": 263, "x": 584, "size": 3, "id": "Plant_0", "label": "Plant"}, {"y": 259, "x": 78, "size": 3, "id": "Stool_0", "label": "Stool"}, {"y": 110, "x": 541, "size": 3, "id": "Window05_0", "label": "Window"}, {"y": 91, "x": 136, "size": 3, "id": "Window05_1", "label": "Window"}, {"y": 344, "x": 138, "size": 3, "id": "Sofa_0", "label": "Sofa"}, {"y": 223, "x": 350, "size": 3, "id": "Fireplace_0", "label": "Fireplace"}, {"y": 346, "x": 357, "size": 3, "id": "Rug_0", "label": "Rug"}], "edges": [{"source": "Stool_0", "label": "on", "id": 8, "target": "Sofa_0"}, {"source": "Fireplace_0", "label": "aboveC", "id": 20, "target": "Rug_0"}]}