{"nodes": [{"y": 264, "x": 420, "size": 3, "id": "Doll06_0", "label": "person"}, {"y": 222, "x": 144, "size": 3, "id": "Doll11_0", "label": "person"}, {"y": 291, "x": 464, "size": 3, "id": "Puppy01_0", "label": "Puppy"}, {"y": 305, "x": 635, "size": 3, "id": "Cat01_0", "label": "Cat"}, {"y": 122, "x": 569, "size": 3, "id": "Window02_0", "label": "Window"}, {"y": 267, "x": 159, "size": 3, "id": "Sofa_0", "label": "Sofa"}, {"y": 312, "x": 638, "size": 3, "id": "PetBed_0", "label": "PetBed"}, {"y": 237, "x": 201, "size": 3, "id": "PopCan_0", "label": "PopCan"}], "edges": [{"source": "Doll06_0", "label": "near", "id": 0, "target": "Doll11_0"}, {"source": "Doll06_0", "label": "beside", "id": 1, "target": "Puppy01_0"}, {"source": "Doll06_0", "label": "near", "id": 4, "target": "Sofa_0"}, {"source": "Doll11_0", "label": "on", "id": 10, "target": "Sofa_0"}, {"source": "Doll11_0", "label": "beside", "id": 12, "target": "PopCan_0"}, {"source": "PetBed_0", "label": "surrounds", "id": 20, "target": "Cat01_0"}, {"source": "Sofa_0", "label": "surrounds", "id": 26, "target": "PopCan_0"}]}