{"nodes": [{"y": 230, "x": 213, "size": 3, "id": "Doll08_0", "label": "person"}, {"y": 64, "x": 600, "size": 3, "id": "sun_0", "label": "sun"}, {"y": 280, "x": 389, "size": 3, "id": "pond_0", "label": "pond"}, {"y": 66, "x": 94, "size": 3, "id": "cloud_0", "label": "cloud"}, {"y": 55, "x": 394, "size": 3, "id": "cloud_1", "label": "cloud"}, {"y": 252, "x": 105, "size": 3, "id": "bench_0", "label": "bench"}, {"y": 254, "x": 589, "size": 3, "id": "blanket_0", "label": "blanket"}, {"y": 228, "x": 266, "size": 3, "id": "mushroom_0", "label": "mushroom"}], "edges": [{"source": "Doll08_0", "label": "near", "id": 1, "target": "pond_0"}, {"source": "Doll08_0", "label": "near", "id": 4, "target": "bench_0"}, {"source": "Doll08_0", "label": "beside", "id": 6, "target": "mushroom_0"}]}