{"nodes": [{"y": 268, "x": 231, "size": 5, "id": "Doll19_0", "label": "person"}, {"y": 272, "x": 398, "size": 5, "id": "Doll19_1", "label": "person"}, {"y": 289, "x": 347, "size": 3, "id": "Puppy01_0", "label": "Puppy"}, {"y": 299, "x": 346, "size": 3, "id": "Rug_0", "label": "Rug"}, {"y": 156, "x": 615, "size": 3, "id": "Door_0", "label": "Door"}, {"y": 98, "x": 351, "size": 3, "id": "Window03_0", "label": "Window"}, {"y": 102, "x": 115, "size": 3, "id": "Picture_0", "label": "Picture"}, {"y": 276, "x": 310, "size": 3, "id": "Toy_0", "label": "Toy"}, {"y": 274, "x": 390, "size": 3, "id": "Toy_1", "label": "Toy"}, {"y": 299, "x": 454, "size": 3, "id": "Toy_2", "label": "Toy"}, {"y": 242, "x": 278, "size": 5, "id": "Toy_3", "label": "Toy"}], "edges": [{"source": "Doll19_0", "label": "beside_infront", "id": 1, "target": "Puppy01_0"}, {"source": "Doll19_0", "label": "beside_infront", "id": 2, "target": "Rug_0"}, {"source": "Doll19_0", "label": "beside_infront", "id": 6, "target": "Toy_0"}, {"source": "Doll19_0", "label": "beside", "id": 9, "target": "Toy_3"}, {"source": "Doll19_1", "label": "beside_infront", "id": 10, "target": "Puppy01_0"}, {"source": "Doll19_1", "label": "beside_infront", "id": 11, "target": "Rug_0"}, {"source": "Doll19_1", "label": "beside_infront", "id": 15, "target": "Toy_0"}, {"source": "Doll19_1", "label": "beside_infront", "id": 16, "target": "Toy_1"}, {"source": "Doll19_1", "label": "beside_infront", "id": 17, "target": "Toy_2"}, {"source": "Doll19_1", "label": "beside", "id": 18, "target": "Toy_3"}, {"source": "Rug_0", "label": "surrounds", "id": 19, "target": "Puppy01_0"}, {"source": "Puppy01_0", "label": "beside", "id": 23, "target": "Toy_0"}, {"source": "Puppy01_0", "label": "beside", "id": 24, "target": "Toy_1"}, {"source": "Puppy01_0", "label": "beside", "id": 25, "target": "Toy_2"}, {"source": "Puppy01_0", "label": "beside_behind", "id": 26, "target": "Toy_3"}, {"source": "Rug_0", "label": "surrounds", "id": 30, "target": "Toy_0"}, {"source": "Rug_0", "label": "surrounds", "id": 31, "target": "Toy_1"}, {"source": "Rug_0", "label": "surrounds", "id": 32, "target": "Toy_2"}, {"source": "Toy_3", "label": "beside_infront", "id": 33, "target": "Rug_0"}, {"source": "Toy_0", "label": "beside", "id": 49, "target": "Toy_1"}, {"source": "Toy_0", "label": "beside", "id": 50, "target": "Toy_2"}, {"source": "Toy_1", "label": "beside", "id": 52, "target": "Toy_2"}, {"source": "Toy_1", "label": "beside_behind", "id": 53, "target": "Toy_3"}]}