{"nodes": [{"y": 150, "x": 354, "size": 3, "id": "Doll15_0", "label": "person"}, {"y": 227, "x": 92, "size": 5, "id": "Doll17_0", "label": "person"}, {"y": 153, "x": 246, "size": 3, "id": "Doll10_0", "label": "person"}, {"y": 152, "x": 430, "size": 2, "id": "Doll16_0", "label": "person"}, {"y": 54, "x": 305, "size": 3, "id": "sun_0", "label": "sun"}, {"y": 171, "x": 601, "size": 3, "id": "bush_0", "label": "bush"}, {"y": 370, "x": 30, "size": 3, "id": "bush_1", "label": "bush"}, {"y": 380, "x": 121, "size": 3, "id": "bush_2", "label": "bush"}, {"y": 110, "x": 648, "size": 3, "id": "tree_0", "label": "tree"}, {"y": 104, "x": 79, "size": 3, "id": "tree_1", "label": "tree"}, {"y": 113, "x": 169, "size": 3, "id": "tree_2", "label": "tree"}, {"y": 110, "x": 512, "size": 1, "id": "tree_3", "label": "tree"}], "edges": [{"source": "Doll15_0", "label": "near", "id": 2, "target": "Doll16_0"}, {"source": "Doll17_0", "label": "opposite_infront", "id": 12, "target": "Doll16_0"}, {"source": "Doll10_0", "label": "near", "id": 21, "target": "Doll16_0"}, {"source": "Doll10_0", "label": "on", "id": 28, "target": "tree_2"}, {"source": "tree_3", "label": "surrounds", "id": 37, "target": "Doll16_0"}, {"source": "bush_0", "label": "on", "id": 47, "target": "tree_0"}, {"source": "bush_1", "label": "on", "id": 51, "target": "bush_2"}, {"source": "tree_1", "label": "on", "id": 63, "target": "tree_2"}]}