{"nodes": [{"y": 226, "x": 629, "size": 3, "id": "Doll16_0", "label": "person"}, {"y": 222, "x": 109, "size": 3, "id": "Doll06_0", "label": "person"}, {"y": 324, "x": 382, "size": 3, "id": "Puppy01_0", "label": "Puppy"}, {"y": 238, "x": 250, "size": 3, "id": "Cat02_0", "label": "Cat"}, {"y": 264, "x": 565, "size": 3, "id": "Couch_0", "label": "Couch"}, {"y": 246, "x": 189, "size": 3, "id": "Couch_1", "label": "Couch"}, {"y": 91, "x": 454, "size": 3, "id": "Window03_0", "label": "Window"}, {"y": 343, "x": 275, "size": 3, "id": "Rug_0", "label": "Rug"}, {"y": 256, "x": 378, "size": 3, "id": "Plant_0", "label": "Plant"}, {"y": 354, "x": 33, "size": 3, "id": "Yarn_0", "label": "Yarn"}, {"y": 226, "x": 636, "size": 3, "id": "cup_0", "label": "cup"}, {"y": 245, "x": 155, "size": 3, "id": "Book_0", "label": "Book"}], "edges": [{"source": "Doll16_0", "label": "opposite", "id": 0, "target": "Doll06_0"}, {"source": "Doll16_0", "label": "near", "id": 1, "target": "Puppy01_0"}, {"source": "Doll16_0", "label": "opposite", "id": 2, "target": "Cat02_0"}, {"source": "Couch_0", "label": "surrounds", "id": 3, "target": "Doll16_0"}, {"source": "Doll06_0", "label": "opposite", "id": 11, "target": "Puppy01_0"}, {"source": "Doll06_0", "label": "near", "id": 12, "target": "Cat02_0"}, {"source": "Doll06_0", "label": "on", "id": 14, "target": "Couch_1"}, {"source": "Doll06_0", "label": "above", "id": 18, "target": "Yarn_0"}, {"source": "Doll06_0", "label": "beside", "id": 20, "target": "Book_0"}, {"source": "Rug_0", "label": "surrounds", "id": 25, "target": "Puppy01_0"}, {"source": "Puppy01_0", "label": "belowC", "id": 26, "target": "Plant_0"}, {"source": "Couch_1", "label": "surrounds", "id": 31, "target": "Cat02_0"}, {"source": "Cat02_0", "label": "aboveC", "id": 33, "target": "Rug_0"}, {"source": "Cat02_0", "label": "beside", "id": 37, "target": "Book_0"}, {"source": "Couch_0", "label": "surrounds", "id": 43, "target": "cup_0"}, {"source": "Couch_1", "label": "surrounds", "id": 50, "target": "Book_0"}]}