{"nodes": [{"y": 335, "x": 302, "size": 3, "id": "Cat01_0", "label": "Cat"}, {"y": 248, "x": 427, "size": 5, "id": "Plant_0", "label": "Plant"}, {"y": 264, "x": 110, "size": 3, "id": "Couch_0", "label": "Couch"}, {"y": 235, "x": 311, "size": 1, "id": "Chair02_0", "label": "Chair"}, {"y": 116, "x": 584, "size": 3, "id": "Window02_0", "label": "Window"}, {"y": 345, "x": 394, "size": 3, "id": "Rug_0", "label": "Rug"}], "edges": [{"source": "Rug_0", "label": "surrounds", "id": 4, "target": "Cat01_0"}]}