{"nodes": [{"y": 224.7999267578125, "x": 111, "size": 3, "id": "Doll06_0", "label": "person"}, {"y": 354.4000244140625, "x": 247.79998779296875, "size": 3, "id": "Doll19_0", "label": "person"}, {"y": 349.5999755859375, "x": 386.1999816894531, "size": 3, "id": "Doll19_1", "label": "person"}, {"y": 51.2000732421875, "x": 339, "size": 3, "id": "Picture_0", "label": "Picture"}, {"y": 310.4000244140625, "x": 591, "size": 3, "id": "Table_0", "label": "Table"}, {"y": 207.9998779296875, "x": 581.3999633789062, "size": 5, "id": "TV_0", "label": "TV"}, {"y": 69.60003662109375, "x": 587, "size": 3, "id": "Window05_0", "label": "Window"}, {"y": 73.5999755859375, "x": 115, "size": 3, "id": "Window05_1", "label": "Window"}, {"y": 195.199951171875, "x": 41.400001525878906, "size": 3, "id": "CoatRack_0", "label": "CoatRack"}, {"y": 211.199951171875, "x": 669.4000244140625, "size": 3, "id": "Plant_0", "label": "Plant"}, {"y": 288.1300048828125, "x": 62.19999694824219, "size": 3, "id": "Sofa_0", "label": "Sofa"}, {"y": 354.4000244140625, "x": 351.79998779296875, "size": 3, "id": "Rug_0", "label": "Rug"}, {"y": 234.4000244140625, "x": 363, "size": 3, "id": "Fireplace_0", "label": "Fireplace"}, {"y": 354.4000244140625, "x": 317.3999938964844, "size": 3, "id": "BuildingToy_0", "label": "BuildingToy"}, {"y": 168, "x": 363, "size": 3, "id": "teaset_0", "label": "teaset"}, {"y": 188.7999267578125, "x": 137.39999389648438, "size": 3, "id": "cup_0", "label": "cup"}], "edges": [{"source": "Doll06_0", "label": "near", "id": 0, "target": "Doll19_0"}, {"source": "Doll06_0", "label": "beside", "id": 7, "target": "CoatRack_0"}, {"source": "Doll06_0", "label": "on", "id": 9, "target": "Sofa_0"}, {"source": "Doll06_0", "label": "belowC", "id": 14, "target": "cup_0"}, {"source": "Rug_0", "label": "surrounds", "id": 24, "target": "Doll19_0"}, {"source": "Rug_0", "label": "surrounds", "id": 37, "target": "Doll19_1"}, {"source": "Doll19_1", "label": "beside", "id": 39, "target": "BuildingToy_0"}, {"source": "CoatRack_0", "label": "on", "id": 93, "target": "Sofa_0"}, {"source": "Rug_0", "label": "surrounds", "id": 111, "target": "BuildingToy_0"}, {"source": "teaset_0", "label": "aboveC", "id": 115, "target": "Fireplace_0"}]}