{"nodes": [{"y": 228, "x": 200, "size": 3, "id": "Doll18_0", "label": "person"}, {"y": 88, "x": 632, "size": 3, "id": "cloud_0", "label": "cloud"}, {"y": 65, "x": 270, "size": 3, "id": "cloud_1", "label": "cloud"}, {"y": 195, "x": 574, "size": 3, "id": "tree_0", "label": "tree"}, {"y": 279, "x": 196, "size": 3, "id": "log_0", "label": "log"}, {"y": 85, "x": 624, "size": 3, "id": "sun_0", "label": "sun"}], "edges": [{"source": "Doll18_0", "label": "aboveC", "id": 3, "target": "log_0"}, {"source": "cloud_0", "label": "on", "id": 6, "target": "tree_0"}]}