{"nodes": [{"y": 101, "x": 160, "size": 3, "id": "Owl_0", "label": "Owl"}, {"y": 281, "x": 133, "size": 3, "id": "Dog01_0", "label": "Dog"}, {"y": 227, "x": 243, "size": 3, "id": "Dog01_1", "label": "Dog"}, {"y": 336, "x": 613, "size": 3, "id": "bush_0", "label": "bush"}, {"y": 125, "x": 92, "size": 3, "id": "tree_0", "label": "tree"}, {"y": 46, "x": 382, "size": 3, "id": "cloud_0", "label": "cloud"}, {"y": 138, "x": 583, "size": 3, "id": "cloud_1", "label": "cloud"}], "edges": [{"source": "Owl_0", "label": "above", "id": 0, "target": "Dog01_0"}, {"source": "Owl_0", "label": "above", "id": 1, "target": "Dog01_1"}, {"source": "tree_0", "label": "surrounds", "id": 3, "target": "Owl_0"}, {"source": "Dog01_0", "label": "below", "id": 8, "target": "tree_0"}]}