{"nodes": [{"y": 169, "x": 560, "size": 3, "id": "Doll12_0", "label": "person"}, {"y": 230, "x": 379, "size": 3, "id": "Doll18_0", "label": "person"}, {"y": 145, "x": 638, "size": 5, "id": "Doll19_0", "label": "person"}, {"y": 213, "x": 126, "size": 4, "id": "Doll09_0", "label": "person"}, {"y": 259, "x": 153, "size": 4, "id": "bench_0", "label": "bench"}, {"y": 259, "x": 592, "size": 5, "id": "slide_0", "label": "slide"}, {"y": 145, "x": 637, "size": 3, "id": "bush_0", "label": "bush"}, {"y": 117, "x": 512, "size": 3, "id": "bush_1", "label": "bush"}, {"y": 115, "x": 47, "size": 3, "id": "bush_2", "label": "bush"}, {"y": 150, "x": 162, "size": 3, "id": "bush_3", "label": "bush"}, {"y": 141, "x": 334, "size": 3, "id": "bush_4", "label": "bush"}, {"y": 31, "x": 587, "size": 1, "id": "cloud_0", "label": "cloud"}, {"y": 13, "x": 310, "size": 3, "id": "cloud_1", "label": "cloud"}, {"y": 64, "x": 204, "size": 3, "id": "cloud_2", "label": "cloud"}, {"y": 40, "x": 412, "size": 3, "id": "cloud_3", "label": "cloud"}, {"y": 40, "x": 80, "size": 1, "id": "sun_0", "label": "sun"}, {"y": 295, "x": 366, "size": 2, "id": "jumprope_0", "label": "jumprope"}, {"y": 218, "x": 189, "size": 3, "id": "soccer_0", "label": "soccer"}, {"y": 230, "x": 178, "size": 5, "id": "soccer_1", "label": "soccer"}], "edges": [{"source": "Doll12_0", "label": "opposite", "id": 0, "target": "Doll18_0"}, {"source": "Doll12_0", "label": "opposite_behind", "id": 1, "target": "Doll19_0"}, {"source": "Doll12_0", "label": "opposite", "id": 2, "target": "Doll09_0"}, {"source": "Doll12_0", "label": "on", "id": 5, "target": "bush_0"}, {"source": "Doll12_0", "label": "on", "id": 6, "target": "bush_1"}, {"source": "Doll18_0", "label": "opposite_behind", "id": 18, "target": "Doll19_0"}, {"source": "Doll18_0", "label": "opposite", "id": 19, "target": "Doll09_0"}, {"source": "Doll18_0", "label": "on", "id": 32, "target": "jumprope_0"}, {"source": "Doll19_0", "label": "opposite", "id": 35, "target": "Doll09_0"}, {"source": "bush_0", "label": "surrounds", "id": 38, "target": "Doll19_0"}, {"source": "Doll09_0", "label": "on", "id": 51, "target": "bench_0"}, {"source": "Doll09_0", "label": "near", "id": 64, "target": "soccer_0"}, {"source": "Doll09_0", "label": "near", "id": 65, "target": "soccer_1"}, {"source": "bench_0", "label": "surrounds", "id": 78, "target": "soccer_0"}, {"source": "bench_0", "label": "surrounds", "id": 79, "target": "soccer_1"}]}