{"nodes": [{"y": 243, "x": 644, "size": 3, "id": "Doll16_0", "label": "person"}, {"y": 193, "x": 433, "size": 3, "id": "Doll03_0", "label": "person"}, {"y": 196, "x": 521, "size": 3, "id": "Doll06_0", "label": "person"}, {"y": 292, "x": 77, "size": 1, "id": "Puppy02_0", "label": "Puppy"}, {"y": 286, "x": 650, "size": 1, "id": "Cat02_0", "label": "Cat"}, {"y": 26, "x": 133, "size": 3, "id": "Owl_0", "label": "Owl"}, {"y": 263, "x": 238, "size": 1, "id": "Squirrel_0", "label": "Squirrel"}, {"y": 333, "x": 87, "size": 3, "id": "blanket_0", "label": "blanket"}, {"y": 312, "x": 380, "size": 3, "id": "grill_0", "label": "grill"}, {"y": 152, "x": 173, "size": 3, "id": "tree_0", "label": "tree"}, {"y": 223, "x": 571, "size": 3, "id": "plate_0", "label": "plate"}, {"y": 327, "x": 165, "size": 1, "id": "plate_1", "label": "plate"}, {"y": 323, "x": 167, "size": 1, "id": "plate_2", "label": "plate"}, {"y": 319, "x": 168, "size": 1, "id": "plate_3", "label": "plate"}, {"y": 288, "x": 149, "size": 3, "id": "bottle_0", "label": "bottle"}, {"y": 259, "x": 356, "size": 3, "id": "hotdog_0", "label": "hotdog"}, {"y": 370, "x": 98, "size": 1, "id": "jumprope_0", "label": "jumprope"}, {"y": 215, "x": 569, "size": 3, "id": "hamburger_0", "label": "hamburger"}, {"y": 263, "x": 373, "size": 3, "id": "hamburger_1", "label": "hamburger"}, {"y": 260, "x": 396, "size": 3, "id": "hamburger_2", "label": "hamburger"}], "edges": [{"source": "Doll16_0", "label": "opposite", "id": 0, "target": "Doll03_0"}, {"source": "Doll16_0", "label": "near", "id": 1, "target": "Doll06_0"}, {"source": "Doll16_0", "label": "near", "id": 16, "target": "hamburger_0"}, {"source": "Doll03_0", "label": "near", "id": 19, "target": "Doll06_0"}, {"source": "Doll03_0", "label": "above", "id": 25, "target": "grill_0"}, {"source": "Doll03_0", "label": "near", "id": 34, "target": "hamburger_0"}, {"source": "Doll03_0", "label": "above", "id": 35, "target": "hamburger_1"}, {"source": "Doll03_0", "label": "above", "id": 36, "target": "hamburger_2"}, {"source": "Doll06_0", "label": "beside", "id": 44, "target": "plate_0"}, {"source": "Doll06_0", "label": "beside", "id": 51, "target": "hamburger_0"}, {"source": "Doll06_0", "label": "near", "id": 52, "target": "hamburger_1"}, {"source": "Doll06_0", "label": "near", "id": 53, "target": "hamburger_2"}, {"source": "Puppy02_0", "label": "aboveC", "id": 66, "target": "jumprope_0"}, {"source": "tree_0", "label": "surrounds", "id": 88, "target": "Owl_0"}, {"source": "tree_0", "label": "surrounds", "id": 101, "target": "Squirrel_0"}, {"source": "blanket_0", "label": "surrounds", "id": 115, "target": "plate_1"}, {"source": "blanket_0", "label": "surrounds", "id": 116, "target": "plate_2"}, {"source": "blanket_0", "label": "surrounds", "id": 117, "target": "plate_3"}, {"source": "bottle_0", "label": "on", "id": 118, "target": "blanket_0"}, {"source": "grill_0", "label": "surrounds", "id": 130, "target": "hotdog_0"}, {"source": "grill_0", "label": "surrounds", "id": 133, "target": "hamburger_1"}, {"source": "grill_0", "label": "surrounds", "id": 134, "target": "hamburger_2"}, {"source": "bottle_0", "label": "on", "id": 139, "target": "tree_0"}, {"source": "plate_0", "label": "on", "id": 151, "target": "hamburger_0"}, {"source": "plate_1", "label": "on", "id": 154, "target": "plate_2"}, {"source": "plate_1", "label": "belowC", "id": 155, "target": "plate_3"}, {"source": "plate_2", "label": "on", "id": 162, "target": "plate_3"}, {"source": "hamburger_1", "label": "beside", "id": 189, "target": "hamburger_2"}]}