{"nodes": [{"y": 191, "x": 207, "size": 3, "id": "Doll12_0", "label": "person"}, {"y": 230, "x": 402, "size": 3, "id": "Puppy01_0", "label": "Puppy"}, {"y": 237, "x": 372, "size": 3, "id": "Couch_0", "label": "Couch"}, {"y": 69, "x": 370, "size": 3, "id": "Window05_0", "label": "Window"}, {"y": 155, "x": 75, "size": 3, "id": "Bookshelf_0", "label": "Bookshelf"}, {"y": 260, "x": 105, "size": 3, "id": "Notebook_0", "label": "Notebook"}, {"y": 208, "x": 37, "size": 3, "id": "Notebook_1", "label": "Notebook"}, {"y": 222, "x": 155, "size": 3, "id": "Book_0", "label": "Book"}, {"y": 106, "x": 96, "size": 3, "id": "Book_1", "label": "Book"}, {"y": 52, "x": 62, "size": 3, "id": "Book_2", "label": "Book"}, {"y": 293, "x": 632, "size": 3, "id": "PetBed_0", "label": "PetBed"}], "edges": [{"source": "Doll12_0", "label": "near", "id": 1, "target": "Couch_0"}, {"source": "Doll12_0", "label": "beside", "id": 3, "target": "Bookshelf_0"}, {"source": "Doll12_0", "label": "beside", "id": 4, "target": "Notebook_0"}, {"source": "Doll12_0", "label": "near", "id": 5, "target": "Notebook_1"}, {"source": "Doll12_0", "label": "beside", "id": 6, "target": "Book_0"}, {"source": "Doll12_0", "label": "beside", "id": 7, "target": "Book_1"}, {"source": "Doll12_0", "label": "near", "id": 8, "target": "Book_2"}, {"source": "Couch_0", "label": "surrounds", "id": 10, "target": "Puppy01_0"}, {"source": "Bookshelf_0", "label": "surrounds", "id": 34, "target": "Notebook_0"}, {"source": "Bookshelf_0", "label": "surrounds", "id": 35, "target": "Notebook_1"}, {"source": "Book_0", "label": "beside", "id": 36, "target": "Bookshelf_0"}, {"source": "Bookshelf_0", "label": "surrounds", "id": 37, "target": "Book_1"}, {"source": "Bookshelf_0", "label": "surrounds", "id": 38, "target": "Book_2"}, {"source": "Notebook_0", "label": "beside", "id": 40, "target": "Notebook_1"}, {"source": "Notebook_0", "label": "beside", "id": 41, "target": "Book_0"}, {"source": "Notebook_0", "label": "below", "id": 42, "target": "Book_1"}, {"source": "Notebook_0", "label": "below", "id": 43, "target": "Book_2"}, {"source": "Notebook_1", "label": "beside", "id": 45, "target": "Book_0"}, {"source": "Notebook_1", "label": "belowC", "id": 46, "target": "Book_1"}, {"source": "Notebook_1", "label": "below", "id": 47, "target": "Book_2"}, {"source": "Book_0", "label": "belowC", "id": 49, "target": "Book_1"}, {"source": "Book_0", "label": "below", "id": 50, "target": "Book_2"}, {"source": "Book_1", "label": "belowC", "id": 52, "target": "Book_2"}]}