{"nodes": [{"y": 229, "x": 560, "size": 3, "id": "Doll10_0", "label": "person"}, {"y": 239, "x": 143, "size": 3, "id": "Doll07_0", "label": "person"}, {"y": 334, "x": 28, "size": 3, "id": "Cat02_0", "label": "Cat"}, {"y": 135, "x": 369, "size": 3, "id": "Picture_0", "label": "Picture"}, {"y": 302, "x": 362, "size": 5, "id": "DiningTable_0", "label": "DiningTable"}, {"y": 116, "x": 611, "size": 3, "id": "Window02_0", "label": "Window"}, {"y": 124, "x": 102, "size": 3, "id": "Window02_1", "label": "Window"}, {"y": 282, "x": 585, "size": 3, "id": "Chair01_0", "label": "Chair"}, {"y": 287, "x": 126, "size": 3, "id": "Chair01_1", "label": "Chair"}, {"y": 219, "x": 477, "size": 3, "id": "bottle_0", "label": "bottle"}, {"y": 237, "x": 228, "size": 3, "id": "bottle_1", "label": "bottle"}, {"y": 228, "x": 350, "size": 3, "id": "bottle_2", "label": "bottle"}, {"y": 232, "x": 382, "size": 3, "id": "bottle_3", "label": "bottle"}], "edges": [{"source": "Doll10_0", "label": "opposite", "id": 0, "target": "Doll07_0"}, {"source": "Doll10_0", "label": "opposite", "id": 1, "target": "Cat02_0"}, {"source": "Doll10_0", "label": "near", "id": 2, "target": "Picture_0"}, {"source": "Doll10_0", "label": "near_behind", "id": 3, "target": "DiningTable_0"}, {"source": "Doll10_0", "label": "below", "id": 4, "target": "Window02_0"}, {"source": "Doll10_0", "label": "aboveC", "id": 6, "target": "Chair01_0"}, {"source": "Doll10_0", "label": "beside", "id": 8, "target": "bottle_0"}, {"source": "Doll10_0", "label": "near", "id": 10, "target": "bottle_2"}, {"source": "Doll10_0", "label": "near", "id": 11, "target": "bottle_3"}, {"source": "Doll07_0", "label": "near", "id": 12, "target": "Cat02_0"}, {"source": "Doll07_0", "label": "near", "id": 13, "target": "Picture_0"}, {"source": "Doll07_0", "label": "near_behind", "id": 14, "target": "DiningTable_0"}, {"source": "Doll07_0", "label": "below", "id": 16, "target": "Window02_1"}, {"source": "Doll07_0", "label": "aboveC", "id": 18, "target": "Chair01_1"}, {"source": "Doll07_0", "label": "beside", "id": 20, "target": "bottle_1"}, {"source": "Doll07_0", "label": "near", "id": 21, "target": "bottle_2"}, {"source": "Doll07_0", "label": "near", "id": 22, "target": "bottle_3"}, {"source": "Cat02_0", "label": "below", "id": 26, "target": "Window02_1"}, {"source": "bottle_2", "label": "belowC", "id": 40, "target": "Picture_0"}, {"source": "bottle_3", "label": "belowC", "id": 41, "target": "Picture_0"}, {"source": "bottle_0", "label": "beside", "id": 74, "target": "bottle_3"}, {"source": "bottle_2", "label": "beside", "id": 77, "target": "bottle_3"}]}