{"nodes": [{"y": 219, "x": 481, "size": 3, "id": "Doll18_0", "label": "person"}, {"y": 202, "x": 270, "size": 4, "id": "Doll09_0", "label": "person"}, {"y": 190, "x": 129, "size": 1, "id": "Racoon_0", "label": "Racoon"}, {"y": 312, "x": 567, "size": 1, "id": "Koi_0", "label": "Koi"}, {"y": 94, "x": 190, "size": 3, "id": "Bee_0", "label": "Bee"}, {"y": 346, "x": 683, "size": 1, "id": "Turtle_0", "label": "Turtle"}, {"y": 140, "x": 139, "size": 1, "id": "bush_0", "label": "bush"}, {"y": 141, "x": 50, "size": 1, "id": "bush_1", "label": "bush"}, {"y": 39, "x": 516, "size": 3, "id": "sun_0", "label": "sun"}, {"y": 289, "x": 274, "size": 4, "id": "log_0", "label": "log"}, {"y": 119, "x": 76, "size": 1, "id": "tree_0", "label": "tree"}, {"y": 107, "x": 647, "size": 1, "id": "tree_1", "label": "tree"}, {"y": 320, "x": 598, "size": 1, "id": "pond_0", "label": "pond"}, {"y": 105, "x": 536, "size": 3, "id": "cloud_0", "label": "cloud"}, {"y": 56, "x": 332, "size": 3, "id": "cloud_1", "label": "cloud"}, {"y": 353, "x": 237, "size": 3, "id": "cup_0", "label": "cup"}, {"y": 363, "x": 249, "size": 4, "id": "cup_1", "label": "cup"}, {"y": 207, "x": 413, "size": 3, "id": "marshmallow_0", "label": "marshmallow"}, {"y": 194, "x": 330, "size": 3, "id": "marshmallow_1", "label": "marshmallow"}, {"y": 44, "x": 75, "size": 3, "id": "nest_0", "label": "nest"}, {"y": 302, "x": 410, "size": 5, "id": "campfire_0", "label": "campfire"}, {"y": 362, "x": 190, "size": 3, "id": "plate_0", "label": "plate"}], "edges": [{"source": "Doll18_0", "label": "opposite", "id": 0, "target": "Doll09_0"}, {"source": "Doll18_0", "label": "beside", "id": 16, "target": "marshmallow_0"}, {"source": "Doll18_0", "label": "near", "id": 17, "target": "marshmallow_1"}, {"source": "Doll09_0", "label": "above", "id": 28, "target": "log_0"}, {"source": "Doll09_0", "label": "near", "id": 37, "target": "marshmallow_1"}, {"source": "Racoon_0", "label": "belowC", "id": 44, "target": "bush_0"}, {"source": "tree_0", "label": "surrounds", "id": 48, "target": "Racoon_0"}, {"source": "pond_0", "label": "surrounds", "id": 68, "target": "Koi_0"}, {"source": "tree_0", "label": "surrounds", "id": 83, "target": "Bee_0"}, {"source": "tree_0", "label": "surrounds", "id": 114, "target": "bush_0"}, {"source": "tree_0", "label": "surrounds", "id": 128, "target": "bush_1"}, {"source": "sun_0", "label": "aboveC", "id": 144, "target": "cloud_0"}, {"source": "marshmallow_1", "label": "above", "id": 161, "target": "log_0"}, {"source": "tree_0", "label": "surrounds", "id": 173, "target": "nest_0"}]}